tifftopdf/__init__.py
tifftopdf/cli.py
tifftopdf/config.py
tifftopdf/models.py
tifftopdf/detection/__init__.py
tifftopdf/detection/blank_detector.py
tifftopdf/grouping/__init__.py
tifftopdf/grouping/grouper.py
tifftopdf/merging/__init__.py
tifftopdf/merging/tiff_to_pdf.py
tifftopdf/orchestrator/__init__.py
tifftopdf/orchestrator/run.py
tifftopdf/reporting/__init__.py
tifftopdf/reporting/metadata_writer.py
tifftopdf/reporting/query.py
tifftopdf/scanning/__init__.py
tifftopdf/scanning/scanner.py
tifftopdf/utils/__init__.py
tifftopdf/utils/helpers.py
tifftopdf/utils/logging.py
tifftopdf-0.2.9.dist-info/licenses/LICENSE
tifftopdf-0.2.9.dist-info/METADATA
tifftopdf-0.2.9.dist-info/WHEEL
tifftopdf-0.2.9.dist-info/entry_points.txt
tifftopdf-0.2.9.dist-info/top_level.txt
tifftopdf-0.2.9.dist-info/RECORD
