Metadata-Version: 2.4
Name: tifftopdf
Version: 0.2.9
Summary: Batch pipeline to group TIFFs by blank-page separators and merge them into PDFs with metadata and verbose CLI.
Author: yannickRafael
License: MIT
Requires-Python: >=3.9
License-File: LICENSE
Requires-Dist: Pillow>=9.3.0
Requires-Dist: opencv-python-headless>=4.7.0
Requires-Dist: numpy>=1.24.0
Requires-Dist: PyPDF2>=3.0.0
Dynamic: license-file
